pathplannerlib/__init__.py
pathplannerlib/auto.py
pathplannerlib/commands.py
pathplannerlib/config.py
pathplannerlib/controller.py
pathplannerlib/events.py
pathplannerlib/logging.py
pathplannerlib/path.py
pathplannerlib/pathfinders.py
pathplannerlib/pathfinding.py
pathplannerlib/telemetry.py
pathplannerlib/trajectory.py
pathplannerlib/util/__init__.py
pathplannerlib/util/swerve.py
robotpy_pathplannerlib-2026.1.2.dist-info/licenses/LICENSE
robotpy_pathplannerlib-2026.1.2.dist-info/METADATA
robotpy_pathplannerlib-2026.1.2.dist-info/WHEEL
robotpy_pathplannerlib-2026.1.2.dist-info/top_level.txt
robotpy_pathplannerlib-2026.1.2.dist-info/RECORD
