Metadata-Version: 2.4
Name: robotpy-pathplannerlib
Version: 2026.1.2
Summary: Python implementation of PathPlannerLib
Author-email: mjansen4857 <mjansen4857@gmail.com>
License: MIT License
Project-URL: Homepage, https://github.com/mjansen4857/pathplanner
Keywords: pathplannerlib
Classifier: License :: OSI Approved :: MIT License
Classifier: Programming Language :: Python
Classifier: Programming Language :: Python :: 3
Requires-Python: >=3.8
License-File: LICENSE
Requires-Dist: pyntcore>=2026.1.1
Requires-Dist: robotpy-wpimath>=2026.1.1
Requires-Dist: robotpy-commands-v2>=2026.1.1
Requires-Dist: robotpy-wpiutil>=2026.1.1
Requires-Dist: robotpy-hal>=2026.1.1
Requires-Dist: numpy>=2.1.1
Dynamic: license-file
